pubmed_papers/__init__.py
pubmed_papers/__main__.py
pubmed_papers/fetch_papers.py
pubmed_papers/results.csv
pubmed_papers_divya1227-0.1.0.dist-info/entry_points.txt
pubmed_papers_divya1227-0.1.0.dist-info/METADATA
pubmed_papers_divya1227-0.1.0.dist-info/WHEEL
pubmed_papers_divya1227-0.1.0.dist-info/RECORD
